jp_1/__init__.py
jp_1/module_1_jp_1.py
jp_1/module_2_jp_1.py
jp1924_setup_test_11-0.4.dist-info/METADATA
jp1924_setup_test_11-0.4.dist-info/WHEEL
jp1924_setup_test_11-0.4.dist-info/top_level.txt
jp1924_setup_test_11-0.4.dist-info/RECORD
