Metadata-Version: 2.1
Name: jp1924-setup-test-11
Version: 0.4
Summary: ['# github_study', '# 12332', '# 12332', '# 12332', '# 12332', '# 12332', '# 12332', '# 12332', '# 12332', '', '# 12332', 'v', '# 12332', '', '']
Home-page: https://github.com/jp1924/pypi_upload
Author: jp
Author-email: jsb1012129@gmail.com
License: UNKNOWN
Platform: UNKNOWN
Requires-Python: >=3.6.0
Requires-Dist: wheel
Requires-Dist: setuptools
